README
setup.py
google_input_parser/InputParser.py
google_input_parser/__init__.py
google_input_parser.egg-info/PKG-INFO
google_input_parser.egg-info/SOURCES.txt
google_input_parser.egg-info/dependency_links.txt
google_input_parser.egg-info/top_level.txt